somfy_connected_thermostat/__init__.py
somfy_connected_thermostat/auth.py
somfy_connected_thermostat/models.py
pySomfyConnectedThermostat-0.0.2.dist-info/LICENSE
pySomfyConnectedThermostat-0.0.2.dist-info/METADATA
pySomfyConnectedThermostat-0.0.2.dist-info/WHEEL
pySomfyConnectedThermostat-0.0.2.dist-info/top_level.txt
pySomfyConnectedThermostat-0.0.2.dist-info/RECORD
